{
  "host": "Хост",
  "enter_host": "Введите хост",
  "port": "Порт",
  "enter_port": "Введите порт",
  "edit_host": "Изменить хост",
  "scan": "Сканировать",
  "save": "Сохранить",
  "settings": "Настройки",
  "product_catalog": "Каталог продукции",
  "port_or_host_empty_error": "Ошибка: порт или хост не заполнены",
  "error": "Ошибка",
  "clear": "Очистить",
  "add_mark": "Добавить маркировку",
  "cant_double_mark": "Нельзя добавлять существующую маркировку",
  "connection_error": "Не удалось подключиться. Проверьте хост, порт или подключение к Wi-Fi.",
  "server_error": "Ошибка сервера. Попробуйте позже.",
  "timeout_error": "Время ожидания истекло. Проверьте соединение с интернетом.",
  "not_found_error": "Данные не найдены.",
  "bad_request_error": "Некорректный запрос.",
  "unauthorized_error": "Ошибка авторизации. Пожалуйста, войдите заново.",
  "forbidden_error": "Доступ запрещён.",
  "unknown_error": "Произошла неизвестная ошибка."
}